pycountsblee25/__init__.py
pycountsblee25/plotting.py
pycountsblee25/pycountsblee25.py
pycountsblee25-0.1.0.dist-info/LICENSE
pycountsblee25-0.1.0.dist-info/METADATA
pycountsblee25-0.1.0.dist-info/WHEEL
pycountsblee25-0.1.0.dist-info/RECORD
