Metadata-Version: 2.3
Name: pycountsblee25
Version: 0.1.0
Summary: Calculate the word counts in a text file
License: MIT
Author: Bryan Lee
Requires-Python: >=3.11,<4.0
Classifier: License :: OSI Approved :: MIT License
Classifier: Programming Language :: Python :: 3
Classifier: Programming Language :: Python :: 3.11
Classifier: Programming Language :: Python :: 3.12
Classifier: Programming Language :: Python :: 3.13
Requires-Dist: matplotlib (>=3.10.0,<4.0.0)
